[
  {
    "flowerId": null,
    "name": "Alstroemerias",
    "price": 2.79,
    "color": "Khaki",
    "amount": 38
  },
  {
    "flowerId": null,
    "name": "Ranunculus",
    "price": 8.54,
    "color": "Crimson",
    "amount": 44
  },
  {
    "flowerId": null,
    "name": "Roses",
    "price": 6.45,
    "color": "Red",
    "amount": 26
  },
  {
    "flowerId": null,
    "name": "Hyacinth",
    "price": 2.42,
    "color": "Orange",
    "amount": 41
  },
  {
    "flowerId": null,
    "name": "Lamiaceae",
    "price": 8.28,
    "color": "Orange",
    "amount": 38
  },
  {
    "flowerId": null,
    "name": "Tulips",
    "price": 3.67,
    "color": "Red",
    "amount": 23
  },
  {
    "flowerId": null,
    "name": "Tulips",
    "price": 4.22,
    "color": "Yellow",
    "amount": 40
  },
  {
    "flowerId": null,
    "name": "Roses",
    "price": 5.0,
    "color": "White",
    "amount": 22
  },
  {
    "flowerId": null,
    "name": "Roses",
    "price": 6.09,
    "color": "Pink",
    "amount": 25
  },
  {
    "flowerId": null,
    "name": "Gerbera",
    "price": 9.17,
    "color": "Goldenrod",
    "amount": 46
  },
  {
    "flowerId": null,
    "name": "Dahlia",
    "price": 2.71,
    "color": "Khaki",
    "amount": 41
  },
  {
    "flowerId": null,
    "name": "Chrysanthemum",
    "price": 3.99,
    "color": "Aquamarine",
    "amount": 44
  },
  {
    "flowerId": null,
    "name": "Zinnia",
    "price": 3.5,
    "color": "Aquamarine",
    "amount": 31
  },
  {
    "flowerId": null,
    "name": "Iris",
    "price": 4.64,
    "color": "Puce",
    "amount": 46
  },
  {
    "flowerId": null,
    "name": "Hydrangea",
    "price": 8.62,
    "color": "Aquamarine",
    "amount": 28
  },
  {
    "flowerId": null,
    "name": "Daffodil",
    "price": 6.96,
    "color": "Mauv",
    "amount": 38
  },
  {
    "flowerId": null,
    "name": "Daffodil",
    "price": 1.69,
    "color": "Pink",
    "amount": 26
  },
  {
    "flowerId": null,
    "name": "Zinnia",
    "price": 3.01,
    "color": "Blue",
    "amount": 43
  },
  {
    "flowerId": null,
    "name": "Ranunculus",
    "price": 1.76,
    "color": "Purple",
    "amount": 37
  }
]